nage/__init__.py
nage/__main__.py
nage/ai_client.py
nage/main.py
nage/parse.py
nage/setting.py
nage-1.2.1.dist-info/METADATA
nage-1.2.1.dist-info/WHEEL
nage-1.2.1.dist-info/entry_points.txt
nage-1.2.1.dist-info/licenses/LICENSE.txt
nage-1.2.1.dist-info/RECORD
