Metadata-Version: 2.4
Name: nage
Version: 1.2.1
Summary: A free AI assistant by 0x3st.
Project-URL: Homepage, https://github.com/0x3st/nage
Project-URL: Repository, https://github.com/0x3st/nage.git
Project-URL: Issues, https://github.com/0x3st/nage/issues
Author-email: 0x3st <findmethroughemail@gmail.com>
License-File: LICENSE.txt
Requires-Python: >=3.8
Requires-Dist: click>=8.0.0
Requires-Dist: openai>=1.0.0
Requires-Dist: pyperclip>=1.8.0
Provides-Extra: build
Requires-Dist: pyinstaller>=5.0.0; extra == 'build'
Provides-Extra: test
Requires-Dist: pytest-cov>=4.0.0; extra == 'test'
Requires-Dist: pytest-mock>=3.10.0; extra == 'test'
Requires-Dist: pytest>=7.0.0; extra == 'test'
